README.md
setup.py
rpvm/__init__.py
rpvm/opcodes.py
rpvm/vm.py
rpvm.egg-info/PKG-INFO
rpvm.egg-info/SOURCES.txt
rpvm.egg-info/dependency_links.txt
rpvm.egg-info/requires.txt
rpvm.egg-info/top_level.txt
tests/__init__.py
tests/test_first.py
tests/test_second.py
tests/utils.py