Metadata-Version: 2.1
Name: rpvm
Version: 0.1.0a1
Summary: Restricted Python Virtual Machine
Home-page: https://github.com/namuyan/rpvm
Author: namuyan
License: MIT Licence
Platform: UNKNOWN
Classifier: Programming Language :: Python :: 3.6
Classifier: License :: OSI Approved :: MIT License
